stlts/__init__.py
stlts/benchmarks.py
stlts/constants.py
stlts/linear_expression.py
stlts/main_constraints.py
stlts/milp_helper.py
stlts/problem.py
stlts/result_helper.py
stlts/rss_distance.py
stlts/rss_scenario.py
stlts/stl.py
stlts/stl_atomic.py
stlts/stl_base.py
stlts/stl_convert.py
stlts/system_model.py
stlts/trace.py
stlts/validator.py
stlts/visualize.py
tests/test_benchmark.py
stlts-1.0.2.dist-info/LICENSE
stlts-1.0.2.dist-info/METADATA
stlts-1.0.2.dist-info/WHEEL
stlts-1.0.2.dist-info/top_level.txt
stlts-1.0.2.dist-info/RECORD
