Metadata-Version: 2.1
Name: stlts
Version: 1.0.2
Summary: Synthesizing a trace that satisfies a given Signal Temporal Logic (STL) formula.
Author-email: Sota Sato <sotasato@nii.ac.jp>
License: MIT License
Project-URL: Homepage, https://github.com/midoriao/stlts
Project-URL: Repository, https://github.com/midoriao/stlts
Requires-Python: >=3.8
License-File: LICENSE
Requires-Dist: numpy
Requires-Dist: gurobipy >=11.0.0
Requires-Dist: scipy
Requires-Dist: matplotlib
Requires-Dist: pandas
Requires-Dist: plotly ==5.20.0
Provides-Extra: dev
Requires-Dist: pytest ; extra == 'dev'
Requires-Dist: flake8 ; extra == 'dev'
Requires-Dist: mypy ; extra == 'dev'
Requires-Dist: black ; extra == 'dev'
Requires-Dist: isort ; extra == 'dev'
